deadlinks/__init__.py
deadlinks/__main__.py
deadlinks/__version__.py
deadlinks/baseurl.py
deadlinks/clicker.py
deadlinks/crawler.py
deadlinks/exceptions.py
deadlinks/index.py
deadlinks/link.py
deadlinks/options.py
deadlinks/request.py
deadlinks/robots_txt.py
deadlinks/settings.py
deadlinks/status.py
deadlinks/url.py
deadlinks/exporters/__init__.py
deadlinks/exporters/default.py
deadlinks/exporters/export.py
deadlinks/serving/__init__.py
deadlinks/serving/handler.py
deadlinks/serving/options.py
deadlinks/serving/router.py
deadlinks/serving/simple_server.py
deadlinks-0.3.2.dist-info/LICENSE
deadlinks-0.3.2.dist-info/METADATA
deadlinks-0.3.2.dist-info/WHEEL
deadlinks-0.3.2.dist-info/entry_points.txt
deadlinks-0.3.2.dist-info/top_level.txt
deadlinks-0.3.2.dist-info/RECORD
