Metadata-Version: 2.1
Name: deadlinks
Version: 0.3.2
Summary: Health checks for your documentation links.
Home-page: https://github.com/butuzov/deadlinks
Author: Oleg Butuzov
Author-email: butuzov@made.ua
License: Apache License 2.0
Project-URL: GitHub: repo, https://github.com/butuzov/deadlinks
Project-URL: Bugtracker, https://github.com/butuzov/deadlinks/issues
Project-URL: Documentation, http://deadlinks.readthedocs.io/
Project-URL: Documentation (latest), https://deadlinks.readthedocs.io/en/latest/
Project-URL: Dockerized, https://hub.docker.com/repository/docker/butuzov/deadlinks/
Keywords: documentation,website,spider,crawler,link-checker
Platform: MacOS
Platform: Posix
Platform: Unix
Classifier: Environment :: Console
Classifier: Development Status :: 5 - Production/Stable
Classifier: Intended Audience :: Developers
Classifier: Intended Audience :: System Administrators
Classifier: Topic :: Utilities
Classifier: Topic :: Documentation
Classifier: Topic :: Internet :: WWW/HTTP :: Indexing/Search
Classifier: Topic :: Internet :: WWW/HTTP :: Site Management
Classifier: Topic :: Internet :: WWW/HTTP :: Site Management :: Link Checking
Classifier: Intended Audience :: Developers
Classifier: Intended Audience :: System Administrators
Classifier: Programming Language :: Python :: 3 :: Only
Classifier: Programming Language :: Python :: 3.5
Classifier: Programming Language :: Python :: 3.6
Classifier: Programming Language :: Python :: 3.7
Classifier: Programming Language :: Python :: 3.8
Classifier: License :: OSI Approved :: Apache Software License
Classifier: Operating System :: MacOS
Classifier: Operating System :: POSIX
Classifier: Operating System :: Unix
Classifier: Natural Language :: English
Requires-Python: >=3.5
Requires-Dist: requests (>=2.22.0)
Requires-Dist: click (>=7.0)
Requires-Dist: urllib3 (>=1.25.6)
Requires-Dist: reppy (==0.4.14)
Requires-Dist: six (==1.14.0)
Requires-Dist: PyOpenSSL (==19.1.0) ; python_full_version < "3.6.0"
